goldfinchsong/__init__.py
goldfinchsong/classes.py
goldfinchsong/cli.py
goldfinchsong/settings.py
goldfinchsong/utils.py
goldfinchsong-0.1.4.dist-info/DESCRIPTION.rst
goldfinchsong-0.1.4.dist-info/METADATA
goldfinchsong-0.1.4.dist-info/RECORD
goldfinchsong-0.1.4.dist-info/WHEEL
goldfinchsong-0.1.4.dist-info/entry_points.txt
goldfinchsong-0.1.4.dist-info/metadata.json
goldfinchsong-0.1.4.dist-info/top_level.txt
