Metadata-Version: 2.0
Name: goldfinchsong
Version: 0.1.4
Summary: Easily post tweets from an image library.
Home-page: https://github.com/jga/goldfinchsong
Author: Julio Gonzalez Altamirano
Author-email: devjga@gmail.com
License: MIT
Keywords: twitter api images
Platform: Any
Classifier: Environment :: Web Environment
Classifier: Intended Audience :: Developers
Classifier: License :: OSI Approved :: MIT License
Classifier: Natural Language :: English
Classifier: Operating System :: OS Independent
Classifier: Programming Language :: Python :: 3 :: Only
Classifier: Topic :: Internet :: WWW/HTTP
Requires-Dist: click
Requires-Dist: tinydb
Requires-Dist: tweepy
